{
  "info": {
    "name": "Mentara - Admin",
    "description": "Admin API endpoints for platform management, user oversight, therapist management, analytics, content moderation, and system administration. Requires admin role access.",
    "schema": "https://schema.getpostman.com/json/collection/v2.1.0/collection.json",
    "_postman_id": "admin-collection-v2"
  },
  "auth": {
    "type": "bearer",
    "bearer": [
      {
        "key": "token",
        "value": "{{accessToken}}",
        "type": "string"
      }
    ]
  },
  "event": [
    {
      "listen": "prerequest",
      "script": {
        "type": "text/javascript",
        "exec": [
          "// Ensure admin authentication token is set",
          "if (!pm.environment.get('accessToken')) {",
          "    console.warn('⚠️ Admin access token not set in environment');",
          "}",
          "",
          "// Verify admin role if available",
          "if (pm.environment.get('userRole') !== 'admin') {",
          "    console.warn('⚠️ Admin role required for these endpoints - current role:', pm.environment.get('userRole'));",
          "}",
          "",
          "// Ensure required UUIDs are valid",
          "const uuidRegex = /^[0-9a-f]{8}-[0-9a-f]{4}-[0-9a-f]{4}-[0-9a-f]{4}-[0-9a-f]{12}$/i;",
          "",
          "if (!pm.environment.get('userId') || !uuidRegex.test(pm.environment.get('userId'))) {",
          "    pm.environment.set('userId', '123e4567-e89b-12d3-a456-426614174000');",
          "}",
          "",
          "if (!pm.environment.get('therapistId') || !uuidRegex.test(pm.environment.get('therapistId'))) {",
          "    pm.environment.set('therapistId', '987fcdeb-51a2-43d7-8ace-123456789012');",
          "}",
          "",
          "// Set default date ranges for analytics",
          "const now = new Date();",
          "const weekAgo = new Date(now.getTime() - 7 * 24 * 60 * 60 * 1000);",
          "const monthAgo = new Date(now.getTime() - 30 * 24 * 60 * 60 * 1000);",
          "",
          "pm.environment.set('currentDate', now.toISOString().split('T')[0]);",
          "pm.environment.set('weekAgoDate', weekAgo.toISOString().split('T')[0]);",
          "pm.environment.set('monthAgoDate', monthAgo.toISOString().split('T')[0]);"
        ]
      }
    },
    {
      "listen": "test",
      "script": {
        "type": "text/javascript",
        "exec": [
          "// Common test for response time",
          "pm.test('Response time is under 5 seconds', function () {",
          "    pm.expect(pm.response.responseTime).to.be.below(5000);",
          "});",
          "",
          "// Handle common admin errors",
          "if (pm.response.code === 401) {",
          "    console.error('❌ Authentication failed - check admin access token');",
          "}",
          "",
          "if (pm.response.code === 403) {",
          "    console.error('❌ Insufficient permissions - admin role required');",
          "}",
          "",
          "if (pm.response.code === 404) {",
          "    console.error('❌ Resource not found - check entity IDs');",
          "}",
          "",
          "// Auto-save useful data from successful responses",
          "if (pm.response.code >= 200 && pm.response.code < 300) {",
          "    try {",
          "        const responseJson = pm.response.json();",
          "        ",
          "        // Save therapist application IDs from pending applications",
          "        if (responseJson.applications && Array.isArray(responseJson.applications) && responseJson.applications.length > 0) {",
          "            pm.environment.set('therapistApplicationId', responseJson.applications[0].id);",
          "        }",
          "        ",
          "        // Save user IDs from user lists",
          "        if (responseJson.users && Array.isArray(responseJson.users) && responseJson.users.length > 0) {",
          "            pm.environment.set('sampleUserId', responseJson.users[0].id);",
          "        }",
          "    } catch (e) {",
          "        // Silent fail for non-JSON responses",
          "    }",
          "}"
        ]
      }
    }
  ],
  "item": [
    {
      "name": "Admin User Management",
      "description": "Admin endpoints for managing users (/admin/users)",
      "item": [
        {
          "name": "Get All Users",
          "request": {
            "method": "GET",
            "header": [
              {
                "key": "Authorization",
                "value": "Bearer {{accessToken}}",
                "type": "text"
              }
            ],
            "url": {
              "raw": "{{baseUrl}}/admin/users?role=client&page=1&limit=20&search={{userSearchQuery}}&status=active&sortBy=createdAt&sortOrder=desc",
              "host": ["{{baseUrl}}"],
              "path": ["admin", "users"],
              "query": [
                {
                  "key": "role",
                  "value": "client",
                  "description": "Filter by user role (client, therapist, moderator, admin)"
                },
                {
                  "key": "page",
                  "value": "1"
                },
                {
                  "key": "limit",
                  "value": "20"
                },
                {
                  "key": "search",
                  "value": "{{userSearchQuery}}",
                  "disabled": true
                },
                {
                  "key": "status",
                  "value": "active"
                },
                {
                  "key": "sortBy",
                  "value": "createdAt"
                },
                {
                  "key": "sortOrder",
                  "value": "desc"
                }
              ]
            },
            "description": "Get all users with advanced filtering, search, and pagination. Admin access required."
          },
          "response": []
        },
        {
          "name": "Get User by ID",
          "request": {
            "method": "GET",
            "header": [
              {
                "key": "Authorization",
                "value": "Bearer {{accessToken}}",
                "type": "text"
              }
            ],
            "url": {
              "raw": "{{baseUrl}}/admin/users/{{userId}}",
              "host": ["{{baseUrl}}"],
              "path": ["admin", "users", "{{userId}}"]
            },
            "description": "Get detailed information about a specific user by ID. Admin access required."
          },
          "response": []
        },
        {
          "name": "Suspend User",
          "request": {
            "method": "PUT",
            "header": [
              {
                "key": "Authorization",
                "value": "Bearer {{accessToken}}",
                "type": "text"
              },
              {
                "key": "Content-Type",
                "value": "application/json",
                "type": "text"
              }
            ],
            "body": {
              "mode": "raw",
              "raw": "{\n  \"reason\": \"Violation of community guidelines\",\n  \"duration\": 7\n}"
            },
            "url": {
              "raw": "{{baseUrl}}/admin/users/{{userId}}/suspend",
              "host": ["{{baseUrl}}"],
              "path": ["admin", "users", "{{userId}}", "suspend"]
            },
            "description": "Suspend a user account with reason and optional duration. Admin access required."
          },
          "response": []
        },
        {
          "name": "Unsuspend User",
          "request": {
            "method": "PUT",
            "header": [
              {
                "key": "Authorization",
                "value": "Bearer {{accessToken}}",
                "type": "text"
              }
            ],
            "url": {
              "raw": "{{baseUrl}}/admin/users/{{userId}}/unsuspend",
              "host": ["{{baseUrl}}"],
              "path": ["admin", "users", "{{userId}}", "unsuspend"]
            },
            "description": "Remove suspension from a user account. Admin access required."
          },
          "response": []
        }
      ]
    },
    {
      "name": "Admin Analytics",
      "description": "Analytics endpoints for admin dashboard (/admin/analytics)",
      "item": [
        {
          "name": "Get Platform Overview",
          "request": {
            "method": "GET",
            "header": [
              {
                "key": "Authorization",
                "value": "Bearer {{accessToken}}",
                "type": "text"
              }
            ],
            "url": {
              "raw": "{{baseUrl}}/admin/analytics/overview",
              "host": ["{{baseUrl}}"],
              "path": ["admin", "analytics", "overview"]
            },
            "description": "Get comprehensive platform overview with key metrics for admin dashboard."
          },
          "response": []
        },
        {
          "name": "Get Matching Performance",
          "request": {
            "method": "GET",
            "header": [
              {
                "key": "Authorization",
                "value": "Bearer {{accessToken}}",
                "type": "text"
              }
            ],
            "url": {
              "raw": "{{baseUrl}}/admin/analytics/matching-performance?startDate={{monthAgoDate}}&endDate={{currentDate}}",
              "host": ["{{baseUrl}}"],
              "path": ["admin", "analytics", "matching-performance"],
              "query": [
                {
                  "key": "startDate",
                  "value": "{{monthAgoDate}}"
                },
                {
                  "key": "endDate",
                  "value": "{{currentDate}}"
                }
              ]
            },
            "description": "Get therapist-client matching performance analytics with date range filtering."
          },
          "response": []
        }
      ]
    },
    {
      "name": "Admin Therapist Management",
      "description": "Therapist application and management endpoints (/admin/therapists)",
      "item": [
        {
          "name": "Get Pending Applications",
          "request": {
            "method": "GET",
            "header": [
              {
                "key": "Authorization",
                "value": "Bearer {{accessToken}}",
                "type": "text"
              }
            ],
            "url": {
              "raw": "{{baseUrl}}/admin/therapists/pending?page=1&limit=20&sortBy=submittedAt&sortOrder=asc",
              "host": ["{{baseUrl}}"],
              "path": ["admin", "therapists", "pending"],
              "query": [
                {
                  "key": "page",
                  "value": "1"
                },
                {
                  "key": "limit",
                  "value": "20"
                },
                {
                  "key": "sortBy",
                  "value": "submittedAt"
                },
                {
                  "key": "sortOrder",
                  "value": "asc"
                }
              ]
            },
            "description": "Get all pending therapist applications requiring admin review."
          },
          "response": []
        },
        {
          "name": "Get All Applications",
          "request": {
            "method": "GET",
            "header": [
              {
                "key": "Authorization",
                "value": "Bearer {{accessToken}}",
                "type": "text"
              }
            ],
            "url": {
              "raw": "{{baseUrl}}/admin/therapists/applications?page=1&limit=20&status=pending",
              "host": ["{{baseUrl}}"],
              "path": ["admin", "therapists", "applications"],
              "query": [
                {
                  "key": "page",
                  "value": "1"
                },
                {
                  "key": "limit",
                  "value": "20"
                },
                {
                  "key": "status",
                  "value": "pending"
                }
              ]
            },
            "description": "Get all therapist applications with filtering by status."
          },
          "response": []
        },
        {
          "name": "Get Application Details",
          "request": {
            "method": "GET",
            "header": [
              {
                "key": "Authorization",
                "value": "Bearer {{accessToken}}",
                "type": "text"
              }
            ],
            "url": {
              "raw": "{{baseUrl}}/admin/therapists/{{therapistId}}/details",
              "host": ["{{baseUrl}}"],
              "path": ["admin", "therapists", "{{therapistId}}", "details"]
            },
            "description": "Get detailed information about a specific therapist application."
          },
          "response": []
        },
        {
          "name": "Approve Therapist Application",
          "request": {
            "method": "POST",
            "header": [
              {
                "key": "Authorization",
                "value": "Bearer {{accessToken}}",
                "type": "text"
              },
              {
                "key": "Content-Type",
                "value": "application/json",
                "type": "text"
              }
            ],
            "body": {
              "mode": "raw",
              "raw": "{\n  \"approvalNotes\": \"Application thoroughly reviewed and approved. All credentials verified.\",\n  \"startDate\": \"{{currentDate}}\",\n  \"welcomeMessage\": \"Welcome to Mentara! Your therapist application has been approved.\"\n}"
            },
            "url": {
              "raw": "{{baseUrl}}/admin/therapists/{{therapistId}}/approve",
              "host": ["{{baseUrl}}"],
              "path": ["admin", "therapists", "{{therapistId}}", "approve"]
            },
            "description": "Approve a therapist application with notes and welcome message."
          },
          "response": []
        },
        {
          "name": "Reject Therapist Application",
          "request": {
            "method": "POST",
            "header": [
              {
                "key": "Authorization",
                "value": "Bearer {{accessToken}}",
                "type": "text"
              },
              {
                "key": "Content-Type",
                "value": "application/json",
                "type": "text"
              }
            ],
            "body": {
              "mode": "raw",
              "raw": "{\n  \"rejectionReason\": \"Insufficient clinical experience for specialized practice areas\",\n  \"feedback\": \"Thank you for your interest in joining Mentara. We encourage you to gain additional experience and consider reapplying in the future.\",\n  \"canReapply\": true\n}"
            },
            "url": {
              "raw": "{{baseUrl}}/admin/therapists/{{therapistId}}/reject",
              "host": ["{{baseUrl}}"],
              "path": ["admin", "therapists", "{{therapistId}}", "reject"]
            },
            "description": "Reject a therapist application with detailed feedback."
          },
          "response": []
        },
        {
          "name": "Update Therapist Status",
          "request": {
            "method": "PUT",
            "header": [
              {
                "key": "Authorization",
                "value": "Bearer {{accessToken}}",
                "type": "text"
              },
              {
                "key": "Content-Type",
                "value": "application/json",
                "type": "text"
              }
            ],
            "body": {
              "mode": "raw",
              "raw": "{\n  \"status\": \"under_review\",\n  \"notes\": \"Application shows strong potential. Scheduling verification call.\"\n}"
            },
            "url": {
              "raw": "{{baseUrl}}/admin/therapists/{{therapistId}}/status",
              "host": ["{{baseUrl}}"],
              "path": ["admin", "therapists", "{{therapistId}}", "status"]
            },
            "description": "Update therapist application status with admin notes."
          },
          "response": []
        },
        {
          "name": "Get Therapist Application Metrics",
          "request": {
            "method": "GET",
            "header": [
              {
                "key": "Authorization",
                "value": "Bearer {{accessToken}}",
                "type": "text"
              }
            ],
            "url": {
              "raw": "{{baseUrl}}/admin/therapists/metrics?startDate={{monthAgoDate}}&endDate={{currentDate}}",
              "host": ["{{baseUrl}}"],
              "path": ["admin", "therapists", "metrics"],
              "query": [
                {
                  "key": "startDate",
                  "value": "{{monthAgoDate}}"
                },
                {
                  "key": "endDate",
                  "value": "{{currentDate}}"
                }
              ]
            },
            "description": "Get therapist application metrics and statistics over time period."
          },
          "response": []
        }
      ]
    },
    {
      "name": "Error Handling & Validation",
      "description": "Test endpoints for validation and error scenarios",
      "item": [
        {
          "name": "Access Admin Endpoint Without Admin Role",
          "event": [
            {
              "listen": "test",
              "script": {
                "exec": [
                  "pm.test('Returns 403 for non-admin user', function () {",
                  "    pm.response.to.have.status(403);",
                  "});",
                  "",
                  "pm.test('Error message mentions admin access', function () {",
                  "    const responseJson = pm.response.json();",
                  "    pm.expect(responseJson.message.toLowerCase()).to.include('admin');",
                  "});"
                ],
                "type": "text/javascript"
              }
            }
          ],
          "request": {
            "auth": {
              "type": "bearer",
              "bearer": [
                {
                  "key": "token",
                  "value": "{{clientAccessToken}}",
                  "type": "string"
                }
              ]
            },
            "method": "GET",
            "header": [],
            "url": {
              "raw": "{{baseUrl}}/admin/analytics/overview",
              "host": ["{{baseUrl}}"],
              "path": ["admin", "analytics", "overview"]
            },
            "description": "Test admin access control with non-admin user token (should return 403)."
          },
          "response": []
        },
        {
          "name": "Invalid User ID Format",
          "event": [
            {
              "listen": "test",
              "script": {
                "exec": [
                  "pm.test('Returns 400 for invalid UUID', function () {",
                  "    pm.response.to.have.status(400);",
                  "});",
                  "",
                  "pm.test('Error indicates validation issue', function () {",
                  "    const responseJson = pm.response.json();",
                  "    pm.expect(responseJson.message || responseJson.error).to.exist;",
                  "});"
                ],
                "type": "text/javascript"
              }
            }
          ],
          "request": {
            "method": "GET",
            "header": [
              {
                "key": "Authorization",
                "value": "Bearer {{accessToken}}",
                "type": "text"
              }
            ],
            "url": {
              "raw": "{{baseUrl}}/admin/users/invalid-uuid-format",
              "host": ["{{baseUrl}}"],
              "path": ["admin", "users", "invalid-uuid-format"]
            },
            "description": "Test validation for invalid UUID format in user ID parameter."
          },
          "response": []
        },
        {
          "name": "Invalid Date Range in Analytics",
          "event": [
            {
              "listen": "test",
              "script": {
                "exec": [
                  "pm.test('Returns 400 for invalid date range', function () {",
                  "    pm.response.to.have.status(400);",
                  "});",
                  "",
                  "pm.test('Error message mentions date', function () {",
                  "    const responseJson = pm.response.json();",
                  "    const message = (responseJson.message || responseJson.error || '').toLowerCase();",
                  "    pm.expect(message).to.include('date');",
                  "});"
                ],
                "type": "text/javascript"
              }
            }
          ],
          "request": {
            "method": "GET",
            "header": [
              {
                "key": "Authorization",
                "value": "Bearer {{accessToken}}",
                "type": "text"
              }
            ],
            "url": {
              "raw": "{{baseUrl}}/admin/analytics/matching-performance?startDate=2024-12-31&endDate=2024-01-01",
              "host": ["{{baseUrl}}"],
              "path": ["admin", "analytics", "matching-performance"],
              "query": [
                {
                  "key": "startDate",
                  "value": "2024-12-31"
                },
                {
                  "key": "endDate",
                  "value": "2024-01-01"
                }
              ]
            },
            "description": "Test validation with invalid date range (start date after end date)."
          },
          "response": []
        }
      ]
    }
  ],
  "variable": [
    {
      "key": "baseUrl",
      "value": "http://localhost:3001",
      "type": "string"
    },
    {
      "key": "userId",
      "value": "",
      "type": "string"
    },
    {
      "key": "therapistId",
      "value": "",
      "type": "string"
    },
    {
      "key": "therapistApplicationId",
      "value": "",
      "type": "string"
    },
    {
      "key": "userSearchQuery",
      "value": "",
      "type": "string"
    },
    {
      "key": "currentDate",
      "value": "",
      "type": "string"
    },
    {
      "key": "weekAgoDate",
      "value": "",
      "type": "string"
    },
    {
      "key": "monthAgoDate",
      "value": "",
      "type": "string"
    },
    {
      "key": "clientAccessToken",
      "value": "",
      "type": "string",
      "description": "Non-admin token for testing access control"
    }
  ]
}